docpack_file/__init__.py
docpack_file/handler.py
docpack_file/main.py
docpack_file-0.1.0.dist-info/METADATA
docpack_file-0.1.0.dist-info/WHEEL
docpack_file-0.1.0.dist-info/entry_points.txt
docpack_file-0.1.0.dist-info/RECORD
