Metadata-Version: 2.4
Name: docpack-file
Version: 0.1.0
Summary: A package format for document outlines and resources
Author: MADE:Explorations Team
License-Expression: MIT
Requires-Python: >=3.11
